eks/__init__.py
eks/command_line_args.py
eks/core.py
eks/ibl_paw_multicam_smoother.py
eks/ibl_pupil_smoother.py
eks/marker_array.py
eks/multicam_smoother.py
eks/singlecam_smoother.py
eks/stats.py
eks/utils.py
ensemble_kalman_smoother-4.2.0.dist-info/licenses/LICENSE
ensemble_kalman_smoother-4.2.0.dist-info/METADATA
ensemble_kalman_smoother-4.2.0.dist-info/WHEEL
ensemble_kalman_smoother-4.2.0.dist-info/top_level.txt
ensemble_kalman_smoother-4.2.0.dist-info/RECORD
