Metadata-Version: 2.4
Name: ensemble-kalman-smoother
Version: 4.2.0
Summary: Ensembling and kalman smoothing for pose estimation
Home-page: http://www.github.com/colehurwitz/eks
Author: Cole Hurwitz
Author-email: 
License-File: LICENSE
Requires-Dist: ipykernel
Requires-Dist: jax
Requires-Dist: jaxlib
Requires-Dist: matplotlib
Requires-Dist: numpy
Requires-Dist: opencv-python
Requires-Dist: optax
Requires-Dist: pandas
Requires-Dist: scikit-learn
Requires-Dist: scipy>=1.2.0
Requires-Dist: sleap_io
Requires-Dist: tqdm
Requires-Dist: typeguard
Requires-Dist: typing
Requires-Dist: sleap_io
Requires-Dist: jax
Requires-Dist: jaxlib
Provides-Extra: dev
Requires-Dist: sphinx_rtd_theme; extra == "dev"
Requires-Dist: Sphinx; extra == "dev"
Requires-Dist: flake8; extra == "dev"
Requires-Dist: isort; extra == "dev"
Requires-Dist: pytest; extra == "dev"
Requires-Dist: sphinx-copybutton; extra == "dev"
Requires-Dist: sphinx-rtd-dark-mode; extra == "dev"
Requires-Dist: sphinx-design; extra == "dev"
Requires-Dist: sphinx-automodapi; extra == "dev"
Dynamic: author
Dynamic: description
Dynamic: description-content-type
Dynamic: home-page
Dynamic: license-file
Dynamic: provides-extra
Dynamic: requires-dist
Dynamic: summary
